LICENSE
README.md
setup.py
mcqgen/__init__.py
mcqgen/mcqgen.py
mcqgen.egg-info/PKG-INFO
mcqgen.egg-info/SOURCES.txt
mcqgen.egg-info/dependency_links.txt
mcqgen.egg-info/requires.txt
mcqgen.egg-info/top_level.txt