Metadata-Version: 2.1
Name: mcqgen
Version: 0.1.4
Summary: Generate Multiple Choice Questions, Choices and Correct Answer in JSON Format
Author: Abhilash Mhaisne
License: MIT License
License-File: LICENSE
